{"cameraMode":{"drawMode":0,"name":"Shaded","section":"Shading Mode"},"sceneLighting":true,"audioPlay":false,"sceneViewState":{"showFog":true,"showMaterialUpdate":false,"showSkybox":true,"showFlares":true,"showImageEffects":true,"showParticleSystems":true},"in2DMode":false,"pivot":{"x":34.56928634643555,"y":16.0518798828125,"z":28.963308334350587},"rotation":{"x":0.15772749483585359,"y":0.3538297414779663,"z":-0.06067543104290962,"w":0.9199355244636536},"size":2.3043832778930666,"orthographic":false}